janux/__init__.py
janux/utils.py
janux/graph_builders/__init__.py
janux/graph_builders/build_digraph.py
janux/path_generators/__init__.py
janux/path_generators/base_generator.py
janux/path_generators/basic_generator.py
janux/path_generators/extended_generator.py
janux/path_generators/heuristic_based_generator.py
janux/path_generators/path_gen_params.json
janux/path_generators/path_gen_utils.py
janux/path_generators/wrapper_functions.py
janux/visualizers/__init__.py
janux/visualizers/animate_edge_attributes.py
janux/visualizers/visualization_utils.py
janux/visualizers/visualize_edge_attributes.py
janux/visualizers/visualize_multi_routes.py
janux/visualizers/visualize_single_route.py
janux-1.0.0.dist-info/LICENSE.txt
janux-1.0.0.dist-info/METADATA
janux-1.0.0.dist-info/WHEEL
janux-1.0.0.dist-info/top_level.txt
janux-1.0.0.dist-info/RECORD
