Metadata-Version: 2.2
Name: janux
Version: 1.0.0
Summary: A robust yet simple tool for generating a set of path options in directed graphs. It is designed for efficient routing or creating path options for custom requirements in transportation networks.
Author-email: Ahmet Onur Akman <ahmetonurakman@gmail.com>
License: MIT License
Project-URL: repository, https://github.com/COeXISTENCE-PROJECT/JanuX
Project-URL: Bug Report, https://github.com/COeXISTENCE-PROJECT/JanuX/issues
Keywords: routing,graphs,transportation,networkx,path,enumeration
Classifier: Programming Language :: Python :: 3
Classifier: License :: OSI Approved :: MIT License
Classifier: Operating System :: OS Independent
Requires-Python: >=3.6
License-File: LICENSE.txt
Requires-Dist: beautifulsoup4
Requires-Dist: lxml
Requires-Dist: matplotlib
Requires-Dist: networkx
Requires-Dist: numpy
Requires-Dist: pandas
Requires-Dist: Pillow
Requires-Dist: prettytable
